[
  {
    "comments": [
      {
        "line": 1,
        "value": "#language:pt"
      }
    ],
    "line": 3,
    "elements": [
      {
        "line": 5,
        "name": "enviar mensagem de sucesso",
        "description": "",
        "id": "que-estou-na-tela-de-mensagem;enviar-mensagem-de-sucesso",
        "type": "scenario",
        "keyword": "Cenario",
        "steps": [
          {
            "result": {
              "duration": 5411292700,
              "status": "passed"
            },
            "line": 6,
            "name": "que estou na home",
            "match": {
              "location": "MensageSteps.que_estou_na_home()"
            },
            "keyword": "Dado "
          },
          {
            "result": {
              "duration": 1991770900,
              "status": "passed"
            },
            "line": 7,
            "name": "clico em mensagem",
            "match": {
              "location": "MensageSteps.clico_em_mensagem()"
            },
            "keyword": "Quando "
          },
          {
            "result": {
              "duration": 417564100,
              "status": "passed"
            },
            "line": 8,
            "name": "preencho todos os campos",
            "match": {
              "location": "MensageSteps.preencho_todos_os_campos()"
            },
            "keyword": "E "
          },
          {
            "result": {
              "duration": 101533800,
              "status": "passed"
            },
            "line": 9,
            "name": "clico em enviar mensagem",
            "match": {
              "location": "MensageSteps.clico_em_enviar_mensagem()"
            },
            "keyword": "E "
          },
          {
            "result": {
              "duration": 29292900,
              "status": "passed"
            },
            "line": 10,
            "name": "vejo mensagem com sucesso",
            "match": {
              "location": "MensageSteps.vejo_mensagem_com_sucesso()"
            },
            "keyword": "Entao "
          }
        ]
      }
    ],
    "name": "que estou na tela de mensagem",
    "description": "",
    "id": "que-estou-na-tela-de-mensagem",
    "keyword": "Funcionalidade",
    "uri": "features/mensager.feature",
    "tags": [
      {
        "line": 2,
        "name": "@mensagemComSucesso"
      }
    ]
  }
]